arcadio_client/__init__.py
arcadio_client/achtung.py
arcadio_client/client.py
arcadio_client/game.py
arcadio_client/py.typed
arcadio_client/strategy.py
arcadio_client-0.1.0.dist-info/METADATA
arcadio_client-0.1.0.dist-info/WHEEL
arcadio_client-0.1.0.dist-info/RECORD
