Metadata-Version: 2.4
Name: arcadio-client
Version: 0.1.0
Summary: Reinformcement learning client for the flash-like games.
Requires-Python: >=3.10
Requires-Dist: attrs>=24.2.0
Requires-Dist: cattrs>=24.1.2
Requires-Dist: websockets==12.0
